{
     "testimonialsdata": [ 
          {
               "header": "Janos - Vejle",
               "review": "Har netop haft mine to basguitarer forbi Kaare (Musik Mekanikeren). Kaare udfører et fantastisk og professionelt stykke arbejde, og yder en service der er svær at finde andre steder. 5 stjerner herfra. Tak for det fantastiske stykke arbejde, Kaare!"
          },
          {
               "header": "Simon - Vejle ",
               "review": "Har af flere omgange haft min Fender Jazz Bass inde forbi Kaare for lidt diverse reparationer og opgraderinger, og hver gang har både service og slutresultatet været fantastisk. Kan bestemt anbefale at få sit instrument tilset af Kaare!"
          },
          {
               "header": "Nicolai - Bredal",
               "review": "God service og kompetent arbejde. Kan det ikke laves her, kan det nok ikke laves."
          },
          {
               "header": "Francis - Arhus",
               "review": "Har gennem tiden fået rettet banan hals på en bass og lavet custom saddel. Hurtig og kompetent arbejde."
          },
          {
               "header": "Mick - Viborg ",
               "review": "Fantastic adjustments on my two Martins (OM35 & D28).. thought they sounded good before, but they really sing now! Thank you!"
          },
          {
               "header": "Bo, Børkop",
               "review": "Formidabelt! Hurtigt og effektivt arbejde. Kaare er hurtig til at finde problemet, hvis man ikke ved hvad det er og ikke selv har færdighederne til at klare problemet. Stærkt anbefalet!!!!"
          }
     ] 
}